athanasios/General_Functions.py
athanasios/__init__.py
athanasios-0.1.dist-info/METADATA
athanasios-0.1.dist-info/WHEEL
athanasios-0.1.dist-info/top_level.txt
athanasios-0.1.dist-info/RECORD
