Metadata-Version: 2.1
Name: athanasios
Version: 0.1
Summary: Some General functions I use that are currently useful. Beta version.
Home-page: https://github.com/AthanasiosPetsanis/athanasios
Author: Athanasios Petsanis
Author-email: athpets8@gmail.com
License: UNKNOWN
Platform: UNKNOWN
Classifier: Programming Language :: Python :: 3
Classifier: Operating System :: OS Independent
Requires-Dist: numpy
Requires-Dist: matplotlib
Requires-Dist: statistics
Requires-Dist: datetime
